ra_aid/__init__.py
ra_aid/__main__.py
ra_aid/__version__.py
ra_aid/agent_context.py
ra_aid/agent_utils.py
ra_aid/agents_alias.py
ra_aid/anthropic_message_utils.py
ra_aid/anthropic_token_limiter.py
ra_aid/config.py
ra_aid/dependencies.py
ra_aid/env.py
ra_aid/env_inv.py
ra_aid/env_inv_context.py
ra_aid/exceptions.py
ra_aid/fallback_handler.py
ra_aid/file_listing.py
ra_aid/llm.py
ra_aid/logging_config.py
ra_aid/model_detection.py
ra_aid/models_params.py
ra_aid/project_info.py
ra_aid/project_state.py
ra_aid/provider_strategy.py
ra_aid/tool_configs.py
ra_aid/tool_leaderboard.py
ra_aid/version_check.py
ra_aid/agent_backends/__init__.py
ra_aid/agent_backends/ciayn_agent.py
ra_aid/agents/__init__.py
ra_aid/agents/implementation_agent.py
ra_aid/agents/key_facts_gc_agent.py
ra_aid/agents/key_snippets_gc_agent.py
ra_aid/agents/planning_agent.py
ra_aid/agents/research_agent.py
ra_aid/agents/research_notes_gc_agent.py
ra_aid/callbacks/default_callback_handler.py
ra_aid/chat_models/deepseek_chat.py
ra_aid/console/__init__.py
ra_aid/console/common.py
ra_aid/console/cowboy_messages.py
ra_aid/console/formatting.py
ra_aid/console/output.py
ra_aid/database/__init__.py
ra_aid/database/connection.py
ra_aid/database/migrations.py
ra_aid/database/models.py
ra_aid/database/pydantic_models.py
ra_aid/database/utils.py
ra_aid/database/repositories/__init__.py
ra_aid/database/repositories/config_repository.py
ra_aid/database/repositories/human_input_repository.py
ra_aid/database/repositories/key_fact_repository.py
ra_aid/database/repositories/key_snippet_repository.py
ra_aid/database/repositories/related_files_repository.py
ra_aid/database/repositories/research_note_repository.py
ra_aid/database/repositories/session_repository.py
ra_aid/database/repositories/trajectory_repository.py
ra_aid/database/repositories/work_log_repository.py
ra_aid/database/tests/ra_aid/database/test_connection.py
ra_aid/migrations/002_20250301_212203_add_key_fact_model.py
ra_aid-0.30.2.dist-info/METADATA
ra_aid-0.30.2.dist-info/WHEEL
ra_aid-0.30.2.dist-info/entry_points.txt
ra_aid-0.30.2.dist-info/licenses/LICENSE
ra_aid-0.30.2.dist-info/RECORD
