Metadata-Version: 2.4
Name: ra-aid
Version: 0.30.2
Summary: RA.Aid - ReAct Aid
Project-URL: Homepage, https://github.com/ai-christianson/RA.Aid
Project-URL: Documentation, https://github.com/ai-christianson/RA.Aid#readme
Project-URL: Repository, https://github.com/ai-christianson/RA.Aid.git
Project-URL: Issues, https://github.com/ai-christianson/RA.Aid/issues
Author-email: AI Christianson <ai.christianson@christianson.ai>
License: 
License-File: LICENSE
Keywords: agent,ai,development,langchain,tools
Classifier: Development Status :: 4 - Beta
Classifier: Intended Audience :: Developers
Classifier: License :: OSI Approved :: Apache Software License
Classifier: Programming Language :: Python :: 3
Classifier: Programming Language :: Python :: 3.8
Classifier: Programming Language :: Python :: 3.9
Classifier: Programming Language :: Python :: 3.10
Classifier: Topic :: Software Development :: Libraries :: Python Modules
Requires-Python: >=3.10
Requires-Dist: fastapi>=0.104.0
Requires-Dist: fuzzywuzzy==0.18.0
Requires-Dist: gitpython>=3.1
Requires-Dist: jinja2>=3.1.2
Requires-Dist: langchain-anthropic>=0.3.10
Requires-Dist: langchain-core>=0.3.48
Requires-Dist: langchain-deepseek>=0.1.2
Requires-Dist: langchain-fireworks>=0.2.8
Requires-Dist: langchain-google-genai>=2.1.1
Requires-Dist: langchain-groq>=0.3.1
Requires-Dist: langchain-mcp-adapters>=0.0.5
Requires-Dist: langchain-ollama>=0.3.0
Requires-Dist: langchain-openai>=0.3.10
Requires-Dist: langchain-text-splitters>=0.3.7
Requires-Dist: langchain>=0.3.21
Requires-Dist: langgraph-checkpoint>=2.0.23
Requires-Dist: langgraph-prebuilt>=0.1.7
Requires-Dist: langgraph-sdk>=0.1.59
Requires-Dist: langgraph>=0.3.20
Requires-Dist: litellm>=1.60.6
Requires-Dist: mcp[cli]>=1.4.1
Requires-Dist: packaging
Requires-Dist: pathspec>=0.11.0
Requires-Dist: peewee-migrate>=1.13.0
Requires-Dist: peewee>=3.17.9
Requires-Dist: platformdirs>=3.17.9
Requires-Dist: prompt-toolkit
Requires-Dist: pyte>=0.8.2
Requires-Dist: python-levenshtein>=0.26.1
Requires-Dist: python-magic>=0.4.27
Requires-Dist: rapidfuzz>=3.11.0
Requires-Dist: requests
Requires-Dist: rich>=13.0.0
Requires-Dist: tavily-python>=0.5.0
Requires-Dist: uvicorn>=0.24.0
Requires-Dist: websockets>=12.0
Provides-Extra: dev
Requires-Dist: pytest-cov>=6.0.0; extra == 'dev'
Requires-Dist: pytest-mock>=3.14.0; extra == 'dev'
Requires-Dist: pytest-timeout>=2.2.0; extra == 'dev'
Requires-Dist: pytest>=7.0.0; extra == 'dev'
